MANIFEST.in
README.md
VERSION
pyproject.toml
py_qgis_server.egg-info/PKG-INFO
py_qgis_server.egg-info/SOURCES.txt
py_qgis_server.egg-info/dependency_links.txt
py_qgis_server.egg-info/entry_points.txt
py_qgis_server.egg-info/requires.txt
py_qgis_server.egg-info/top_level.txt
pyqgisserver/__init__.py
pyqgisserver/build.manifest
pyqgisserver/config.py
pyqgisserver/logger.py
pyqgisserver/middleware.py
pyqgisserver/monitor.py
pyqgisserver/plugins.py
pyqgisserver/qgspool.py
pyqgisserver/qgsworker.py
pyqgisserver/runtime.py
pyqgisserver/server.py
pyqgisserver/stats.py
pyqgisserver/tests.py
pyqgisserver/version.py
pyqgisserver/handlers/__init__.py
pyqgisserver/handlers/asynchandler.py
pyqgisserver/handlers/basehandler.py
pyqgisserver/handlers/landingpage.py
pyqgisserver/handlers/oapihandler.py
pyqgisserver/handlers/owshandler.py
pyqgisserver/handlers/statushandler.py
pyqgisserver/management/__init__.py
pyqgisserver/management/server.py
pyqgisserver/management/apis/__init__.py
pyqgisserver/management/apis/cache.py
pyqgisserver/management/apis/handler.py
pyqgisserver/management/apis/plugins.py
pyqgisserver/monitors/amqp.py
pyqgisserver/monitors/base.py
pyqgisserver/monitors/test.py
pyqgisserver/qgscache/__init__.py
pyqgisserver/qgscache/cachemanager.py
pyqgisserver/qgscache/observer.py
pyqgisserver/qgscache/types.py
pyqgisserver/qgscache/handlers/__init__.py
pyqgisserver/qgscache/handlers/file_handler.py
pyqgisserver/qgscache/handlers/postgres_handler.py
pyqgisserver/qgscache/handlers/proto.py
pyqgisserver/qgscache/observers/ban.py
pyqgisserver/qgscache/observers/test.py
pyqgisserver/utils/__init__.py
pyqgisserver/utils/decorators.py
pyqgisserver/utils/lru.py
pyqgisserver/utils/qgis.py
pyqgisserver/utils/stats.py
pyqgisserver/zeromq/__init__.py
pyqgisserver/zeromq/broker.py
pyqgisserver/zeromq/client.py
pyqgisserver/zeromq/messages.py
pyqgisserver/zeromq/pool.py
pyqgisserver/zeromq/supervisor.py
pyqgisserver/zeromq/utils.py
pyqgisserver/zeromq/worker.py
pyqgisservercontrib/core/__init__.py
pyqgisservercontrib/core/componentmanager.py
pyqgisservercontrib/core/filters.py
pyqgisservercontrib/core/watchfiles.py
pyqgisservercontrib/middlewares/__init__.py
pyqgisservercontrib/middlewares/request_logger.py