Metadata-Version: 2.2
Name: py-qgis-server
Version: 1.9.3
Summary: Py-Qgis-Server is an OWS/OGC server built on top of QGIS Server implementation
Author-email: 3Liz <david.marteau@3liz.com>
Maintainer-email: David Marteau <david.marteau@3liz.com>
Project-URL: Homepage, https://github.com/3liz/py-qgis-server
Project-URL: Repository, https://github.com/3liz/py-qgis-server.git
Project-URL: Documentation, https://docs.3liz.org/py-qgis-server
Classifier: License :: OSI Approved :: Mozilla Public License 2.0 (MPL 2.0)
Classifier: Environment :: Web Environment
Classifier: Intended Audience :: Developers
Classifier: Intended Audience :: Science/Research
Classifier: Programming Language :: Python :: 3 :: Only
Classifier: Programming Language :: Python :: 3.8
Classifier: Programming Language :: Python :: 3.9
Classifier: Programming Language :: Python :: 3.10
Classifier: Programming Language :: Python :: 3.11
Classifier: Programming Language :: Python :: 3.12
Classifier: Operating System :: POSIX :: Linux
Classifier: Topic :: Scientific/Engineering :: GIS
Requires-Python: >=3.8
Requires-Dist: tornado>=5
Requires-Dist: pyzmq>=17
Requires-Dist: PyYAML
Requires-Dist: typing-extensions
Requires-Dist: psutil
Provides-Extra: amqp
Requires-Dist: py-amqp-client<2.0.0; extra == "amqp"
